Robotic_Arm/__init__.py
Robotic_Arm/rm_ctypes_wrap.py
Robotic_Arm/rm_robot_interface.py
Robotic_Arm/libs/linux_arm/libapi_c.so
Robotic_Arm/libs/linux_x86/libapi_c.so
Robotic_Arm/libs/win_32/api_c.dll
Robotic_Arm/libs/win_64/api_c.dll
Robotic_Arm_t1-1.1.1rc3.dist-info/METADATA
Robotic_Arm_t1-1.1.1rc3.dist-info/WHEEL
Robotic_Arm_t1-1.1.1rc3.dist-info/top_level.txt
Robotic_Arm_t1-1.1.1rc3.dist-info/RECORD
